cid_cli.py
cid_cli-1.0.dist-info/METADATA
cid_cli-1.0.dist-info/WHEEL
cid_cli-1.0.dist-info/entry_points.txt
cid_cli-1.0.dist-info/top_level.txt
cid_cli-1.0.dist-info/RECORD
