Metadata-Version: 2.1
Name: cid-cli
Version: 1.0
Summary: CLI wrapper for py-cid for decoding CID
Home-page: https://github.com/weaming/cid-cli
Author: weaming
Author-email: garden.yuen@gmail.com
License: UNKNOWN
Project-URL: Source, https://github.com/weaming/cid-cli
Project-URL: Bug Reports, https://github.com/weaming/cid-cli
Keywords: cid,ipfs,filecoin
Platform: UNKNOWN
Requires-Dist: py-cid
